<?xml version="1.0" encoding="utf-8" ?>

<languages>
    <language name="English" id="EN">
        <resourceEditor>
            <searchPanel>
                <choose>Choose...</choose>
                <from>From</from>
                <to>To</to>
                <resourceProvider>Resources provider</resourceProvider>
                <simple>simple</simple>
                <advanced>advanced</advanced>
                <hideTranslated>Hide Translated</hideTranslated>
                <searchPlaceholder>Search</searchPlaceholder>
                <clear>clear</clear>
                <loadTranslations>Load</loadTranslations>
                <resetAllFilters>Reset all filters</resetAllFilters>
            </searchPanel>
            <advancedMode>
                <import>Import</import>
                <exportAll>Export All</exportAll>
                <exportFiltered>Export Filtered</exportFiltered>
            </advancedMode>
            <translations>
                <common>
                    <searchPlaceholder>Search</searchPlaceholder>
                    <clear>clear</clear>
                    <error>Error</error>
                </common>
                <columnHeaders>
                    <key>Key</key>
                    <from>From</from>
                    <to>To</to>
                    <status>Status</status>
                </columnHeaders>
                <loadMore>Load More</loadMore>
                <itemsLoaded>items are loaded out of</itemsLoaded>
                <appliedFilters>Applied filters</appliedFilters>
                <itemsAreShown>items are shown</itemsAreShown>
                <clientFiltersApplied>
                    <key>Key</key>
                    <from>From</from>
                    <to>To</to>
                </clientFiltersApplied>
            </translations>
            <messages>
                <DownloadingTranlsationsForLanguageFinishedFormat>Downloading tranlsations for {0} finished</DownloadingTranlsationsForLanguageFinishedFormat>
                <AllLanguages>All Languages</AllLanguages>
                <NoTranslationsFound>No translations found</NoTranslationsFound>
                <ExportTranslationsQueryIsNotDefined>Export Translations Query is not defined</ExportTranslationsQueryIsNotDefined>
                <SelectFromLanguage>Please choose 'From' language</SelectFromLanguage>
                <SelectToLanguage>Please choose 'To' language</SelectToLanguage>
                <SelectFromAndToLanguages>Please choose 'From' and 'To' languages</SelectFromAndToLanguages>
                <NothingToExportForSelectedLanguageFormat>There is nothing to export for {0} language</NothingToExportForSelectedLanguageFormat>
                <NothingToExport>There is nothing to export</NothingToExport>
                <All>All</All>
                <Saved>Saved</Saved>
            </messages>
        </resourceEditor>
    </language>
</languages>